umi/database/__init__.py
umi/database/database_connector.py
umi_database_connector-1.5.3.dist-info/LICENSE
umi_database_connector-1.5.3.dist-info/METADATA
umi_database_connector-1.5.3.dist-info/WHEEL
umi_database_connector-1.5.3.dist-info/top_level.txt
umi_database_connector-1.5.3.dist-info/RECORD
